{"This":{"Namespace":"System.Threading","Name":"WaitHandle","QualifiedCppName":"System::Threading::WaitHandle","IsGenericTemplate":false,"IsNested":false,"ElementType":null,"GenericParameterConstraints":[],"Generics":[]},"Attributes":[{"Name":"TokenAttribute","RVA":-1,"Offset":-1,"VA":-1},{"Name":"ComVisibleAttribute","RVA":15335848,"Offset":15335848,"VA":-1}],"ImplementingInterfaces":[{"Namespace":"System","Name":"IDisposable","IsGenericParameter":false,"IsArray":false,"IsPointer":false,"Generics":[],"TypeId":3263}],"InstanceFields":[{"Attributes":[{"Name":"TokenAttribute","RVA":-1,"Offset":-1,"VA":-1}],"Name":"waitHandle","Offset":24,"LayoutOffset":-1,"Specifiers":["private"],"Type":{"Namespace":"System","Name":"IntPtr","IsGenericParameter":false,"IsArray":false,"IsPointer":false,"Generics":[],"TypeId":3362},"Constant":null},{"Attributes":[{"Name":"TokenAttribute","RVA":-1,"Offset":-1,"VA":-1}],"Name":"safeWaitHandle","Offset":32,"LayoutOffset":-1,"Specifiers":[],"Type":{"Namespace":"Microsoft.Win32.SafeHandles","Name":"SafeWaitHandle","IsGenericParameter":false,"IsArray":false,"IsPointer":false,"Generics":[],"TypeId":3144},"Constant":null},{"Attributes":[{"Name":"TokenAttribute","RVA":-1,"Offset":-1,"VA":-1}],"Name":"hasThreadAffinity","Offset":40,"LayoutOffset":-1,"Specifiers":[],"Type":{"Namespace":"System","Name":"Boolean","IsGenericParameter":false,"IsArray":false,"IsPointer":false,"Generics":[],"TypeId":3204},"Constant":null}],"Layout":"Sequential","Methods":[{"Attributes":[{"Name":"TokenAttribute","RVA":-1,"Offset":-1,"VA":-1}],"Generic":false,"GenericParameters":[],"HidesBase":false,"Il2CppName":"Init","ImplementedFrom":null,"IsSpecialName":false,"IsVirtual":false,"Name":"Init","Offset":27024652,"Parameters":[],"ReturnType":{"Namespace":"System","Name":"Void","IsGenericParameter":false,"IsArray":false,"IsPointer":false,"Generics":[],"TypeId":3406},"RVA":27024652,"Slot":-1,"Specifiers":["private"],"VA":27024652},{"Attributes":[{"Name":"TokenAttribute","RVA":-1,"Offset":-1,"VA":-1}],"Generic":false,"GenericParameters":[],"HidesBase":false,"Il2CppName":"set_Handle","ImplementedFrom":null,"IsSpecialName":false,"IsVirtual":true,"Name":"set_Handle","Offset":27024776,"Parameters":[{"Type":{"Namespace":"System","Name":"IntPtr","IsGenericParameter":false,"IsArray":false,"IsPointer":false,"Generics":[],"TypeId":3362},"Name":"value","Modifier":"None"}],"ReturnType":{"Namespace":"System","Name":"Void","IsGenericParameter":false,"IsArray":false,"IsPointer":false,"Generics":[],"TypeId":3406},"RVA":27024776,"Slot":7,"Specifiers":["public"],"VA":27024776},{"Attributes":[{"Name":"TokenAttribute","RVA":-1,"Offset":-1,"VA":-1},{"Name":"ReliabilityContractAttribute","RVA":15367056,"Offset":15367056,"VA":-1}],"Generic":false,"GenericParameters":[],"HidesBase":false,"Il2CppName":"get_SafeWaitHandle","ImplementedFrom":null,"IsSpecialName":false,"IsVirtual":false,"Name":"get_SafeWaitHandle","Offset":27025012,"Parameters":[],"ReturnType":{"Namespace":"Microsoft.Win32.SafeHandles","Name":"SafeWaitHandle","IsGenericParameter":false,"IsArray":false,"IsPointer":false,"Generics":[],"TypeId":3144},"RVA":27025012,"Slot":-1,"Specifiers":["public"],"VA":27025012},{"Attributes":[{"Name":"TokenAttribute","RVA":-1,"Offset":-1,"VA":-1},{"Name":"ReliabilityContractAttribute","RVA":15367080,"Offset":15367080,"VA":-1}],"Generic":false,"GenericParameters":[],"HidesBase":false,"Il2CppName":"set_SafeWaitHandle","ImplementedFrom":null,"IsSpecialName":false,"IsVirtual":false,"Name":"set_SafeWaitHandle","Offset":27025200,"Parameters":[{"Type":{"Namespace":"Microsoft.Win32.SafeHandles","Name":"SafeWaitHandle","IsGenericParameter":false,"IsArray":false,"IsPointer":false,"Generics":[],"TypeId":3144},"Name":"value","Modifier":"None"}],"ReturnType":{"Namespace":"System","Name":"Void","IsGenericParameter":false,"IsArray":false,"IsPointer":false,"Generics":[],"TypeId":3406},"RVA":27025200,"Slot":-1,"Specifiers":["public"],"VA":27025200},{"Attributes":[{"Name":"TokenAttribute","RVA":-1,"Offset":-1,"VA":-1}],"Generic":false,"GenericParameters":[],"HidesBase":false,"Il2CppName":"SetHandleInternal","ImplementedFrom":null,"IsSpecialName":false,"IsVirtual":false,"Name":"SetHandleInternal","Offset":27025360,"Parameters":[{"Type":{"Namespace":"Microsoft.Win32.SafeHandles","Name":"SafeWaitHandle","IsGenericParameter":false,"IsArray":false,"IsPointer":false,"Generics":[],"TypeId":3144},"Name":"handle","Modifier":"None"}],"ReturnType":{"Namespace":"System","Name":"Void","IsGenericParameter":false,"IsArray":false,"IsPointer":false,"Generics":[],"TypeId":3406},"RVA":27025360,"Slot":-1,"Specifiers":[],"VA":27025360},{"Attributes":[{"Name":"TokenAttribute","RVA":-1,"Offset":-1,"VA":-1}],"Generic":false,"GenericParameters":[],"HidesBase":false,"Il2CppName":"WaitOne","ImplementedFrom":null,"IsSpecialName":false,"IsVirtual":true,"Name":"WaitOne","Offset":27025416,"Parameters":[{"Type":{"Namespace":"System","Name":"Int32","IsGenericParameter":false,"IsArray":false,"IsPointer":false,"Generics":[],"TypeId":3269},"Name":"millisecondsTimeout","Modifier":"None"},{"Type":{"Namespace":"System","Name":"Boolean","IsGenericParameter":false,"IsArray":false,"IsPointer":false,"Generics":[],"TypeId":3204},"Name":"exitContext","Modifier":"None"}],"ReturnType":{"Namespace":"System","Name":"Boolean","IsGenericParameter":false,"IsArray":false,"IsPointer":false,"Generics":[],"TypeId":3204},"RVA":27025416,"Slot":8,"Specifiers":["public"],"VA":27025416},{"Attributes":[{"Name":"TokenAttribute","RVA":-1,"Offset":-1,"VA":-1}],"Generic":false,"GenericParameters":[],"HidesBase":false,"Il2CppName":"WaitOne","ImplementedFrom":null,"IsSpecialName":false,"IsVirtual":true,"Name":"WaitOne","Offset":27025752,"Parameters":[{"Type":{"Namespace":"System","Name":"TimeSpan","IsGenericParameter":false,"IsArray":false,"IsPointer":false,"Generics":[],"TypeId":3318},"Name":"timeout","Modifier":"None"},{"Type":{"Namespace":"System","Name":"Boolean","IsGenericParameter":false,"IsArray":false,"IsPointer":false,"Generics":[],"TypeId":3204},"Name":"exitContext","Modifier":"None"}],"ReturnType":{"Namespace":"System","Name":"Boolean","IsGenericParameter":false,"IsArray":false,"IsPointer":false,"Generics":[],"TypeId":3204},"RVA":27025752,"Slot":9,"Specifiers":["public"],"VA":27025752},{"Attributes":[{"Name":"TokenAttribute","RVA":-1,"Offset":-1,"VA":-1}],"Generic":false,"GenericParameters":[],"HidesBase":false,"Il2CppName":"WaitOne","ImplementedFrom":null,"IsSpecialName":false,"IsVirtual":true,"Name":"WaitOne","Offset":27026016,"Parameters":[],"ReturnType":{"Namespace":"System","Name":"Boolean","IsGenericParameter":false,"IsArray":false,"IsPointer":false,"Generics":[],"TypeId":3204},"RVA":27026016,"Slot":10,"Specifiers":["public"],"VA":27026016},{"Attributes":[{"Name":"TokenAttribute","RVA":-1,"Offset":-1,"VA":-1}],"Generic":false,"GenericParameters":[],"HidesBase":false,"Il2CppName":"WaitOne","ImplementedFrom":null,"IsSpecialName":false,"IsVirtual":true,"Name":"WaitOne","Offset":27026036,"Parameters":[{"Type":{"Namespace":"System","Name":"Int32","IsGenericParameter":false,"IsArray":false,"IsPointer":false,"Generics":[],"TypeId":3269},"Name":"millisecondsTimeout","Modifier":"None"}],"ReturnType":{"Namespace":"System","Name":"Boolean","IsGenericParameter":false,"IsArray":false,"IsPointer":false,"Generics":[],"TypeId":3204},"RVA":27026036,"Slot":11,"Specifiers":["public"],"VA":27026036},{"Attributes":[{"Name":"TokenAttribute","RVA":-1,"Offset":-1,"VA":-1}],"Generic":false,"GenericParameters":[],"HidesBase":false,"Il2CppName":"WaitOne","ImplementedFrom":null,"IsSpecialName":false,"IsVirtual":true,"Name":"WaitOne","Offset":27026052,"Parameters":[{"Type":{"Namespace":"System","Name":"TimeSpan","IsGenericParameter":false,"IsArray":false,"IsPointer":false,"Generics":[],"TypeId":3318},"Name":"timeout","Modifier":"None"}],"ReturnType":{"Namespace":"System","Name":"Boolean","IsGenericParameter":false,"IsArray":false,"IsPointer":false,"Generics":[],"TypeId":3204},"RVA":27026052,"Slot":12,"Specifiers":["public"],"VA":27026052},{"Attributes":[{"Name":"TokenAttribute","RVA":-1,"Offset":-1,"VA":-1}],"Generic":false,"GenericParameters":[],"HidesBase":false,"Il2CppName":"WaitOne","ImplementedFrom":null,"IsSpecialName":false,"IsVirtual":false,"Name":"WaitOne","Offset":27025608,"Parameters":[{"Type":{"Namespace":"System","Name":"Int64","IsGenericParameter":false,"IsArray":false,"IsPointer":false,"Generics":[],"TypeId":3270},"Name":"timeout","Modifier":"None"},{"Type":{"Namespace":"System","Name":"Boolean","IsGenericParameter":false,"IsArray":false,"IsPointer":false,"Generics":[],"TypeId":3204},"Name":"exitContext","Modifier":"None"}],"ReturnType":{"Namespace":"System","Name":"Boolean","IsGenericParameter":false,"IsArray":false,"IsPointer":false,"Generics":[],"TypeId":3204},"RVA":27025608,"Slot":-1,"Specifiers":["private"],"VA":27025608},{"Attributes":[{"Name":"TokenAttribute","RVA":-1,"Offset":-1,"VA":-1}],"Generic":false,"GenericParameters":[],"HidesBase":false,"Il2CppName":"InternalWaitOne","ImplementedFrom":null,"IsSpecialName":false,"IsVirtual":false,"Name":"InternalWaitOne","Offset":27026068,"Parameters":[{"Type":{"Namespace":"System.Runtime.InteropServices","Name":"SafeHandle","IsGenericParameter":false,"IsArray":false,"IsPointer":false,"Generics":[],"TypeId":4192},"Name":"waitableSafeHandle","Modifier":"None"},{"Type":{"Namespace":"System","Name":"Int64","IsGenericParameter":false,"IsArray":false,"IsPointer":false,"Generics":[],"TypeId":3270},"Name":"millisecondsTimeout","Modifier":"None"},{"Type":{"Namespace":"System","Name":"Boolean","IsGenericParameter":false,"IsArray":false,"IsPointer":false,"Generics":[],"TypeId":3204},"Name":"hasThreadAffinity","Modifier":"None"},{"Type":{"Namespace":"System","Name":"Boolean","IsGenericParameter":false,"IsArray":false,"IsPointer":false,"Generics":[],"TypeId":3204},"Name":"exitContext","Modifier":"None"}],"ReturnType":{"Namespace":"System","Name":"Boolean","IsGenericParameter":false,"IsArray":false,"IsPointer":false,"Generics":[],"TypeId":3204},"RVA":27026068,"Slot":-1,"Specifiers":["static"],"VA":27026068},{"Attributes":[{"Name":"TokenAttribute","RVA":-1,"Offset":-1,"VA":-1},{"Name":"ReliabilityContractAttribute","RVA":15367104,"Offset":15367104,"VA":-1}],"Generic":false,"GenericParameters":[],"HidesBase":false,"Il2CppName":"WaitAny","ImplementedFrom":null,"IsSpecialName":false,"IsVirtual":false,"Name":"WaitAny","Offset":27026712,"Parameters":[{"Type":{"Namespace":"System.Threading","Name":"WaitHandle","IsGenericParameter":false,"IsArray":true,"IsPointer":false,"Generics":[],"TypeId":3721},"Name":"waitHandles","Modifier":"None"},{"Type":{"Namespace":"System","Name":"Int32","IsGenericParameter":false,"IsArray":false,"IsPointer":false,"Generics":[],"TypeId":3269},"Name":"millisecondsTimeout","Modifier":"None"},{"Type":{"Namespace":"System","Name":"Boolean","IsGenericParameter":false,"IsArray":false,"IsPointer":false,"Generics":[],"TypeId":3204},"Name":"exitContext","Modifier":"None"}],"ReturnType":{"Namespace":"System","Name":"Int32","IsGenericParameter":false,"IsArray":false,"IsPointer":false,"Generics":[],"TypeId":3269},"RVA":27026712,"Slot":-1,"Specifiers":["static","public"],"VA":27026712},{"Attributes":[{"Name":"TokenAttribute","RVA":-1,"Offset":-1,"VA":-1},{"Name":"ReliabilityContractAttribute","RVA":15367128,"Offset":15367128,"VA":-1}],"Generic":false,"GenericParameters":[],"HidesBase":false,"Il2CppName":"WaitAny","ImplementedFrom":null,"IsSpecialName":false,"IsVirtual":false,"Name":"WaitAny","Offset":27028248,"Parameters":[{"Type":{"Namespace":"System.Threading","Name":"WaitHandle","IsGenericParameter":false,"IsArray":true,"IsPointer":false,"Generics":[],"TypeId":3721},"Name":"waitHandles","Modifier":"None"},{"Type":{"Namespace":"System","Name":"TimeSpan","IsGenericParameter":false,"IsArray":false,"IsPointer":false,"Generics":[],"TypeId":3318},"Name":"timeout","Modifier":"None"},{"Type":{"Namespace":"System","Name":"Boolean","IsGenericParameter":false,"IsArray":false,"IsPointer":false,"Generics":[],"TypeId":3204},"Name":"exitContext","Modifier":"None"}],"ReturnType":{"Namespace":"System","Name":"Int32","IsGenericParameter":false,"IsArray":false,"IsPointer":false,"Generics":[],"TypeId":3269},"RVA":27028248,"Slot":-1,"Specifiers":["static","public"],"VA":27028248},{"Attributes":[{"Name":"TokenAttribute","RVA":-1,"Offset":-1,"VA":-1}],"Generic":false,"GenericParameters":[],"HidesBase":false,"Il2CppName":"ThrowAbandonedMutexException","ImplementedFrom":null,"IsSpecialName":false,"IsVirtual":false,"Name":"ThrowAbandonedMutexException","Offset":27026616,"Parameters":[],"ReturnType":{"Namespace":"System","Name":"Void","IsGenericParameter":false,"IsArray":false,"IsPointer":false,"Generics":[],"TypeId":3406},"RVA":27026616,"Slot":-1,"Specifiers":["static","private"],"VA":27026616},{"Attributes":[{"Name":"TokenAttribute","RVA":-1,"Offset":-1,"VA":-1}],"Generic":false,"GenericParameters":[],"HidesBase":false,"Il2CppName":"ThrowAbandonedMutexException","ImplementedFrom":null,"IsSpecialName":false,"IsVirtual":false,"Name":"ThrowAbandonedMutexException","Offset":27028132,"Parameters":[{"Type":{"Namespace":"System","Name":"Int32","IsGenericParameter":false,"IsArray":false,"IsPointer":false,"Generics":[],"TypeId":3269},"Name":"location","Modifier":"None"},{"Type":{"Namespace":"System.Threading","Name":"WaitHandle","IsGenericParameter":false,"IsArray":false,"IsPointer":false,"Generics":[],"TypeId":3721},"Name":"handle","Modifier":"None"}],"ReturnType":{"Namespace":"System","Name":"Void","IsGenericParameter":false,"IsArray":false,"IsPointer":false,"Generics":[],"TypeId":3406},"RVA":27028132,"Slot":-1,"Specifiers":["static","private"],"VA":27028132},{"Attributes":[{"Name":"TokenAttribute","RVA":-1,"Offset":-1,"VA":-1}],"Generic":false,"GenericParameters":[],"HidesBase":false,"Il2CppName":"Close","ImplementedFrom":null,"IsSpecialName":false,"IsVirtual":true,"Name":"Close","Offset":27028548,"Parameters":[],"ReturnType":{"Namespace":"System","Name":"Void","IsGenericParameter":false,"IsArray":false,"IsPointer":false,"Generics":[],"TypeId":3406},"RVA":27028548,"Slot":13,"Specifiers":["public"],"VA":27028548},{"Attributes":[{"Name":"TokenAttribute","RVA":-1,"Offset":-1,"VA":-1}],"Generic":false,"GenericParameters":[],"HidesBase":false,"Il2CppName":"Dispose","ImplementedFrom":null,"IsSpecialName":false,"IsVirtual":true,"Name":"Dispose","Offset":27028676,"Parameters":[{"Type":{"Namespace":"System","Name":"Boolean","IsGenericParameter":false,"IsArray":false,"IsPointer":false,"Generics":[],"TypeId":3204},"Name":"explicitDisposing","Modifier":"None"}],"ReturnType":{"Namespace":"System","Name":"Void","IsGenericParameter":false,"IsArray":false,"IsPointer":false,"Generics":[],"TypeId":3406},"RVA":27028676,"Slot":14,"Specifiers":["protected"],"VA":27028676},{"Attributes":[{"Name":"TokenAttribute","RVA":-1,"Offset":-1,"VA":-1}],"Generic":false,"GenericParameters":[],"HidesBase":false,"Il2CppName":"Dispose","ImplementedFrom":null,"IsSpecialName":false,"IsVirtual":true,"Name":"Dispose","Offset":27028752,"Parameters":[],"ReturnType":{"Namespace":"System","Name":"Void","IsGenericParameter":false,"IsArray":false,"IsPointer":false,"Generics":[],"TypeId":3406},"RVA":27028752,"Slot":6,"Specifiers":["public"],"VA":27028752},{"Attributes":[{"Name":"TokenAttribute","RVA":-1,"Offset":-1,"VA":-1}],"Generic":false,"GenericParameters":[],"HidesBase":false,"Il2CppName":"WaitMultiple","ImplementedFrom":null,"IsSpecialName":false,"IsVirtual":false,"Name":"WaitMultiple","Offset":27027492,"Parameters":[{"Type":{"Namespace":"System.Threading","Name":"WaitHandle","IsGenericParameter":false,"IsArray":true,"IsPointer":false,"Generics":[],"TypeId":3721},"Name":"waitHandles","Modifier":"None"},{"Type":{"Namespace":"System","Name":"Int32","IsGenericParameter":false,"IsArray":false,"IsPointer":false,"Generics":[],"TypeId":3269},"Name":"millisecondsTimeout","Modifier":"None"},{"Type":{"Namespace":"System","Name":"Boolean","IsGenericParameter":false,"IsArray":false,"IsPointer":false,"Generics":[],"TypeId":3204},"Name":"exitContext","Modifier":"None"},{"Type":{"Namespace":"System","Name":"Boolean","IsGenericParameter":false,"IsArray":false,"IsPointer":false,"Generics":[],"TypeId":3204},"Name":"WaitAll","Modifier":"None"}],"ReturnType":{"Namespace":"System","Name":"Int32","IsGenericParameter":false,"IsArray":false,"IsPointer":false,"Generics":[],"TypeId":3269},"RVA":27027492,"Slot":-1,"Specifiers":["static","private"],"VA":27027492},{"Attributes":[{"Name":"TokenAttribute","RVA":-1,"Offset":-1,"VA":-1}],"Generic":false,"GenericParameters":[],"HidesBase":false,"Il2CppName":"WaitOneNative","ImplementedFrom":null,"IsSpecialName":false,"IsVirtual":false,"Name":"WaitOneNative","Offset":27026344,"Parameters":[{"Type":{"Namespace":"System.Runtime.InteropServices","Name":"SafeHandle","IsGenericParameter":false,"IsArray":false,"IsPointer":false,"Generics":[],"TypeId":4192},"Name":"waitableSafeHandle","Modifier":"None"},{"Type":{"Namespace":"System","Name":"UInt32","IsGenericParameter":false,"IsArray":false,"IsPointer":false,"Generics":[],"TypeId":3327},"Name":"millisecondsTimeout","Modifier":"None"},{"Type":{"Namespace":"System","Name":"Boolean","IsGenericParameter":false,"IsArray":false,"IsPointer":false,"Generics":[],"TypeId":3204},"Name":"hasThreadAffinity","Modifier":"None"},{"Type":{"Namespace":"System","Name":"Boolean","IsGenericParameter":false,"IsArray":false,"IsPointer":false,"Generics":[],"TypeId":3204},"Name":"exitContext","Modifier":"None"}],"ReturnType":{"Namespace":"System","Name":"Int32","IsGenericParameter":false,"IsArray":false,"IsPointer":false,"Generics":[],"TypeId":3269},"RVA":27026344,"Slot":-1,"Specifiers":["static","private"],"VA":27026344},{"Attributes":[{"Name":"TokenAttribute","RVA":-1,"Offset":-1,"VA":-1}],"Generic":false,"GenericParameters":[],"HidesBase":false,"Il2CppName":"Wait_internal","ImplementedFrom":null,"IsSpecialName":false,"IsVirtual":false,"Name":"Wait_internal","Offset":27028880,"Parameters":[{"Type":{"Namespace":"System","Name":"IntPtr","IsGenericParameter":false,"IsArray":false,"IsPointer":true,"Generics":[],"TypeId":3362},"Name":"handles","Modifier":"None"},{"Type":{"Namespace":"System","Name":"Int32","IsGenericParameter":false,"IsArray":false,"IsPointer":false,"Generics":[],"TypeId":3269},"Name":"numHandles","Modifier":"None"},{"Type":{"Namespace":"System","Name":"Boolean","IsGenericParameter":false,"IsArray":false,"IsPointer":false,"Generics":[],"TypeId":3204},"Name":"waitAll","Modifier":"None"},{"Type":{"Namespace":"System","Name":"Int32","IsGenericParameter":false,"IsArray":false,"IsPointer":false,"Generics":[],"TypeId":3269},"Name":"ms","Modifier":"None"}],"ReturnType":{"Namespace":"System","Name":"Int32","IsGenericParameter":false,"IsArray":false,"IsPointer":false,"Generics":[],"TypeId":3269},"RVA":27028880,"Slot":-1,"Specifiers":["static","private"],"VA":27028880},{"Attributes":[{"Name":"TokenAttribute","RVA":-1,"Offset":-1,"VA":-1}],"Generic":false,"GenericParameters":[],"HidesBase":false,"Il2CppName":".cctor","ImplementedFrom":null,"IsSpecialName":false,"IsVirtual":false,"Name":".cctor","Offset":27028888,"Parameters":[],"ReturnType":{"Namespace":"System","Name":"Void","IsGenericParameter":false,"IsArray":false,"IsPointer":false,"Generics":[],"TypeId":3406},"RVA":27028888,"Slot":-1,"Specifiers":["static","private"],"VA":27028888},{"Attributes":[{"Name":"TokenAttribute","RVA":-1,"Offset":-1,"VA":-1}],"Generic":false,"GenericParameters":[],"HidesBase":true,"Il2CppName":".ctor","ImplementedFrom":{"Namespace":"System","Name":"MarshalByRefObject","IsGenericParameter":false,"IsArray":false,"IsPointer":false,"Generics":[],"TypeId":3364},"IsSpecialName":false,"IsVirtual":false,"Name":".ctor","Offset":27024612,"Parameters":[],"ReturnType":{"Namespace":"System","Name":"Void","IsGenericParameter":false,"IsArray":false,"IsPointer":false,"Generics":[],"TypeId":3406},"RVA":27024612,"Slot":-1,"Specifiers":["protected"],"VA":27024612}],"NestedTypes":[],"Parent":{"Namespace":"System","Name":"MarshalByRefObject","IsGenericParameter":false,"IsArray":false,"IsPointer":false,"Generics":[],"TypeId":3364},"Properties":[{"Attributes":[{"Name":"TokenAttribute","RVA":-1,"Offset":-1,"VA":-1},{"Name":"ObsoleteAttribute","RVA":15372120,"Offset":15372120,"VA":-1}],"Specifiers":["public"],"GetMethod":false,"SetMethod":true,"Name":"Handle","Type":{"Namespace":"System","Name":"IntPtr","IsGenericParameter":false,"IsArray":false,"IsPointer":false,"Generics":[],"TypeId":3362}},{"Attributes":[{"Name":"TokenAttribute","RVA":-1,"Offset":-1,"VA":-1}],"Specifiers":["public"],"GetMethod":true,"SetMethod":true,"Name":"SafeWaitHandle","Type":{"Namespace":"Microsoft.Win32.SafeHandles","Name":"SafeWaitHandle","IsGenericParameter":false,"IsArray":false,"IsPointer":false,"Generics":[],"TypeId":3144}}],"Specifiers":[],"StaticFields":[{"Attributes":[{"Name":"TokenAttribute","RVA":-1,"Offset":-1,"VA":-1}],"Name":"WaitTimeout","Offset":-1,"LayoutOffset":-1,"Specifiers":["static","public"],"Type":{"Namespace":"System","Name":"Int32","IsGenericParameter":false,"IsArray":false,"IsPointer":false,"Generics":[],"TypeId":3269},"Constant":"258"},{"Attributes":[{"Name":"TokenAttribute","RVA":-1,"Offset":-1,"VA":-1}],"Name":"MAX_WAITHANDLES","Offset":-1,"LayoutOffset":-1,"Specifiers":["static","private"],"Type":{"Namespace":"System","Name":"Int32","IsGenericParameter":false,"IsArray":false,"IsPointer":false,"Generics":[],"TypeId":3269},"Constant":"64"},{"Attributes":[{"Name":"TokenAttribute","RVA":-1,"Offset":-1,"VA":-1}],"Name":"WAIT_OBJECT_0","Offset":-1,"LayoutOffset":-1,"Specifiers":["static","private"],"Type":{"Namespace":"System","Name":"Int32","IsGenericParameter":false,"IsArray":false,"IsPointer":false,"Generics":[],"TypeId":3269},"Constant":"0"},{"Attributes":[{"Name":"TokenAttribute","RVA":-1,"Offset":-1,"VA":-1}],"Name":"WAIT_ABANDONED","Offset":-1,"LayoutOffset":-1,"Specifiers":["static","private"],"Type":{"Namespace":"System","Name":"Int32","IsGenericParameter":false,"IsArray":false,"IsPointer":false,"Generics":[],"TypeId":3269},"Constant":"128"},{"Attributes":[{"Name":"TokenAttribute","RVA":-1,"Offset":-1,"VA":-1}],"Name":"WAIT_FAILED","Offset":-1,"LayoutOffset":-1,"Specifiers":["static","private"],"Type":{"Namespace":"System","Name":"Int32","IsGenericParameter":false,"IsArray":false,"IsPointer":false,"Generics":[],"TypeId":3269},"Constant":"2147483647"},{"Attributes":[{"Name":"TokenAttribute","RVA":-1,"Offset":-1,"VA":-1}],"Name":"ERROR_TOO_MANY_POSTS","Offset":-1,"LayoutOffset":-1,"Specifiers":["static","private"],"Type":{"Namespace":"System","Name":"Int32","IsGenericParameter":false,"IsArray":false,"IsPointer":false,"Generics":[],"TypeId":3269},"Constant":"298"},{"Attributes":[{"Name":"TokenAttribute","RVA":-1,"Offset":-1,"VA":-1}],"Name":"InvalidHandle","Offset":0,"LayoutOffset":-1,"Specifiers":["static","protected","readonly"],"Type":{"Namespace":"System","Name":"IntPtr","IsGenericParameter":false,"IsArray":false,"IsPointer":false,"Generics":[],"TypeId":3362},"Constant":null},{"Attributes":[{"Name":"TokenAttribute","RVA":-1,"Offset":-1,"VA":-1}],"Name":"MaxWaitHandles","Offset":-1,"LayoutOffset":-1,"Specifiers":["static"],"Type":{"Namespace":"System","Name":"Int32","IsGenericParameter":false,"IsArray":false,"IsPointer":false,"Generics":[],"TypeId":3269},"Constant":"64"}],"Type":"Class","TypeDefIndex":-1,"Size":41}