{"This":{"Namespace":"System.ComponentModel","Name":"DesignerCategoryAttribute","QualifiedCppName":"::System::ComponentModel::DesignerCategoryAttribute","IsGenericTemplate":false,"IsNested":false,"ElementType":null,"GenericParameterConstraints":[],"Generics":[]},"Attributes":[{"Name":"TokenAttribute","RVA":-1,"Offset":-1,"VA":-1},{"Name":"AttributeUsageAttribute","RVA":16903620,"Offset":16903620,"VA":-1}],"ImplementingInterfaces":[],"InstanceFields":[{"Attributes":[{"Name":"TokenAttribute","RVA":-1,"Offset":-1,"VA":-1}],"Name":"category","Offset":16,"LayoutOffset":-1,"Specifiers":["private"],"Type":{"Namespace":"System","Name":"String","IsGenericParameter":false,"IsArray":false,"IsPointer":false,"Generics":[],"TypeId":3495},"Constant":null},{"Attributes":[{"Name":"TokenAttribute","RVA":-1,"Offset":-1,"VA":-1}],"Name":"typeId","Offset":24,"LayoutOffset":-1,"Specifiers":["private"],"Type":{"Namespace":"System","Name":"String","IsGenericParameter":false,"IsArray":false,"IsPointer":false,"Generics":[],"TypeId":3495},"Constant":null}],"Layout":"Auto","Methods":[{"Attributes":[{"Name":"TokenAttribute","RVA":-1,"Offset":-1,"VA":-1}],"Generic":false,"GenericParameters":[],"HidesBase":false,"Il2CppName":".ctor","ImplementedFrom":null,"IsSpecialName":false,"IsVirtual":false,"Name":".ctor","Offset":30907712,"Parameters":[{"Type":{"Namespace":"System","Name":"String","IsGenericParameter":false,"IsArray":false,"IsPointer":false,"Generics":[],"TypeId":3495},"Name":"category","Modifier":"None"}],"ReturnType":{"Namespace":"System","Name":"Void","IsGenericParameter":false,"IsArray":false,"IsPointer":false,"Generics":[],"TypeId":3594},"RVA":30907712,"Slot":-1,"Specifiers":["public"],"VA":30907712},{"Attributes":[{"Name":"TokenAttribute","RVA":-1,"Offset":-1,"VA":-1}],"Generic":false,"GenericParameters":[],"HidesBase":false,"Il2CppName":"get_Category","ImplementedFrom":null,"IsSpecialName":false,"IsVirtual":false,"Name":"get_Category","Offset":30907756,"Parameters":[],"ReturnType":{"Namespace":"System","Name":"String","IsGenericParameter":false,"IsArray":false,"IsPointer":false,"Generics":[],"TypeId":3495},"RVA":30907756,"Slot":-1,"Specifiers":["public"],"VA":30907756},{"Attributes":[{"Name":"TokenAttribute","RVA":-1,"Offset":-1,"VA":-1}],"Generic":false,"GenericParameters":[],"HidesBase":false,"Il2CppName":".cctor","ImplementedFrom":null,"IsSpecialName":false,"IsVirtual":false,"Name":".cctor","Offset":30908184,"Parameters":[],"ReturnType":{"Namespace":"System","Name":"Void","IsGenericParameter":false,"IsArray":false,"IsPointer":false,"Generics":[],"TypeId":3594},"RVA":30908184,"Slot":-1,"Specifiers":["static","private"],"VA":30908184},{"Attributes":[{"Name":"TokenAttribute","RVA":-1,"Offset":-1,"VA":-1}],"Generic":false,"GenericParameters":[],"HidesBase":true,"Il2CppName":".ctor","ImplementedFrom":{"Namespace":"System","Name":"Attribute","IsGenericParameter":false,"IsArray":false,"IsPointer":false,"Generics":[],"TypeId":3387},"IsSpecialName":false,"IsVirtual":false,"Name":".ctor","Offset":30907612,"Parameters":[],"ReturnType":{"Namespace":"System","Name":"Void","IsGenericParameter":false,"IsArray":false,"IsPointer":false,"Generics":[],"TypeId":3594},"RVA":30907612,"Slot":-1,"Specifiers":["public"],"VA":30907612},{"Attributes":[{"Name":"TokenAttribute","RVA":-1,"Offset":-1,"VA":-1}],"Generic":false,"GenericParameters":[],"HidesBase":false,"Il2CppName":"get_TypeId","ImplementedFrom":{"Namespace":"System","Name":"Attribute","IsGenericParameter":false,"IsArray":false,"IsPointer":false,"Generics":[],"TypeId":3387},"IsSpecialName":false,"IsVirtual":true,"Name":"get_TypeId","Offset":30907764,"Parameters":[],"ReturnType":{"Namespace":"System","Name":"Object","IsGenericParameter":false,"IsArray":false,"IsPointer":false,"Generics":[],"TypeId":3562},"RVA":30907764,"Slot":4,"Specifiers":["public","override"],"VA":30907764},{"Attributes":[{"Name":"TokenAttribute","RVA":-1,"Offset":-1,"VA":-1}],"Generic":false,"GenericParameters":[],"HidesBase":false,"Il2CppName":"Equals","ImplementedFrom":{"Namespace":"System","Name":"Attribute","IsGenericParameter":false,"IsArray":false,"IsPointer":false,"Generics":[],"TypeId":3387},"IsSpecialName":false,"IsVirtual":true,"Name":"Equals","Offset":30907852,"Parameters":[{"Type":{"Namespace":"System","Name":"Object","IsGenericParameter":false,"IsArray":false,"IsPointer":false,"Generics":[],"TypeId":3562},"Name":"obj","Modifier":"None"}],"ReturnType":{"Namespace":"System","Name":"Boolean","IsGenericParameter":false,"IsArray":false,"IsPointer":false,"Generics":[],"TypeId":3392},"RVA":30907852,"Slot":0,"Specifiers":["public","override"],"VA":30907852},{"Attributes":[{"Name":"TokenAttribute","RVA":-1,"Offset":-1,"VA":-1}],"Generic":false,"GenericParameters":[],"HidesBase":false,"Il2CppName":"GetHashCode","ImplementedFrom":{"Namespace":"System","Name":"Attribute","IsGenericParameter":false,"IsArray":false,"IsPointer":false,"Generics":[],"TypeId":3387},"IsSpecialName":false,"IsVirtual":true,"Name":"GetHashCode","Offset":30908016,"Parameters":[],"ReturnType":{"Namespace":"System","Name":"Int32","IsGenericParameter":false,"IsArray":false,"IsPointer":false,"Generics":[],"TypeId":3457},"RVA":30908016,"Slot":2,"Specifiers":["public","override"],"VA":30908016},{"Attributes":[{"Name":"TokenAttribute","RVA":-1,"Offset":-1,"VA":-1}],"Generic":false,"GenericParameters":[],"HidesBase":false,"Il2CppName":"IsDefaultAttribute","ImplementedFrom":{"Namespace":"System","Name":"Attribute","IsGenericParameter":false,"IsArray":false,"IsPointer":false,"Generics":[],"TypeId":3387},"IsSpecialName":false,"IsVirtual":true,"Name":"IsDefaultAttribute","Offset":30908048,"Parameters":[],"ReturnType":{"Namespace":"System","Name":"Boolean","IsGenericParameter":false,"IsArray":false,"IsPointer":false,"Generics":[],"TypeId":3392},"RVA":30908048,"Slot":5,"Specifiers":["public","override"],"VA":30908048}],"NestedTypes":[],"Parent":{"Namespace":"System","Name":"Attribute","IsGenericParameter":false,"IsArray":false,"IsPointer":false,"Generics":[],"TypeId":3387},"Properties":[{"Attributes":[{"Name":"TokenAttribute","RVA":-1,"Offset":-1,"VA":-1}],"Specifiers":["public"],"GetMethod":true,"SetMethod":false,"Name":"Category","Type":{"Namespace":"System","Name":"String","IsGenericParameter":false,"IsArray":false,"IsPointer":false,"Generics":[],"TypeId":3495}},{"Attributes":[{"Name":"TokenAttribute","RVA":-1,"Offset":-1,"VA":-1}],"Specifiers":["public","override"],"GetMethod":true,"SetMethod":false,"Name":"TypeId","Type":{"Namespace":"System","Name":"Object","IsGenericParameter":false,"IsArray":false,"IsPointer":false,"Generics":[],"TypeId":3562}}],"Specifiers":[],"StaticFields":[{"Attributes":[{"Name":"TokenAttribute","RVA":-1,"Offset":-1,"VA":-1}],"Name":"Component","Offset":0,"LayoutOffset":-1,"Specifiers":["static","public","readonly"],"Type":{"Namespace":"System.ComponentModel","Name":"DesignerCategoryAttribute","IsGenericParameter":false,"IsArray":false,"IsPointer":false,"Generics":[],"TypeId":5877},"Constant":null},{"Attributes":[{"Name":"TokenAttribute","RVA":-1,"Offset":-1,"VA":-1}],"Name":"Default","Offset":8,"LayoutOffset":-1,"Specifiers":["static","public","readonly"],"Type":{"Namespace":"System.ComponentModel","Name":"DesignerCategoryAttribute","IsGenericParameter":false,"IsArray":false,"IsPointer":false,"Generics":[],"TypeId":5877},"Constant":null},{"Attributes":[{"Name":"TokenAttribute","RVA":-1,"Offset":-1,"VA":-1}],"Name":"Form","Offset":16,"LayoutOffset":-1,"Specifiers":["static","public","readonly"],"Type":{"Namespace":"System.ComponentModel","Name":"DesignerCategoryAttribute","IsGenericParameter":false,"IsArray":false,"IsPointer":false,"Generics":[],"TypeId":5877},"Constant":null},{"Attributes":[{"Name":"TokenAttribute","RVA":-1,"Offset":-1,"VA":-1}],"Name":"Generic","Offset":24,"LayoutOffset":-1,"Specifiers":["static","public","readonly"],"Type":{"Namespace":"System.ComponentModel","Name":"DesignerCategoryAttribute","IsGenericParameter":false,"IsArray":false,"IsPointer":false,"Generics":[],"TypeId":5877},"Constant":null}],"Type":"Class","TypeDefIndex":-1,"Size":32}