{"This":{"Namespace":"","Name":"LevelGameplaySetupData","QualifiedCppName":"GlobalNamespace::LevelGameplaySetupData","IsGenericTemplate":false,"IsNested":false,"ElementType":null,"GenericParameterConstraints":[],"Generics":[]},"Attributes":[{"Name":"TokenAttribute","RVA":-1,"Offset":-1,"VA":-1}],"ImplementingInterfaces":[{"Namespace":"","Name":"ILevelGameplaySetupData","IsGenericParameter":false,"IsArray":false,"IsPointer":false,"Generics":[],"TypeId":1689}],"InstanceFields":[{"Attributes":[{"Name":"TokenAttribute","RVA":-1,"Offset":-1,"VA":-1}],"Name":"_gameplayModifiers","Offset":16,"LayoutOffset":-1,"Specifiers":["private"],"Type":{"Namespace":"","Name":"GameplayModifiers","IsGenericParameter":false,"IsArray":false,"IsPointer":false,"Generics":[],"TypeId":1008},"Constant":null},{"Attributes":[{"Name":"TokenAttribute","RVA":-1,"Offset":-1,"VA":-1},{"Name":"CompilerGeneratedAttribute","RVA":14919128,"Offset":14919128,"VA":-1}],"Name":"<beatmapLevel>k__BackingField","Offset":24,"LayoutOffset":-1,"Specifiers":["private"],"Type":{"Namespace":"","Name":"IPreviewBeatmapLevel","IsGenericParameter":false,"IsArray":false,"IsPointer":false,"Generics":[],"TypeId":1641},"Constant":null},{"Attributes":[{"Name":"TokenAttribute","RVA":-1,"Offset":-1,"VA":-1},{"Name":"CompilerGeneratedAttribute","RVA":14919144,"Offset":14919144,"VA":-1}],"Name":"<beatmapCharacteristic>k__BackingField","Offset":32,"LayoutOffset":-1,"Specifiers":["private"],"Type":{"Namespace":"","Name":"BeatmapCharacteristicSO","IsGenericParameter":false,"IsArray":false,"IsPointer":false,"Generics":[],"TypeId":1596},"Constant":null},{"Attributes":[{"Name":"TokenAttribute","RVA":-1,"Offset":-1,"VA":-1},{"Name":"CompilerGeneratedAttribute","RVA":14919160,"Offset":14919160,"VA":-1}],"Name":"<beatmapDifficulty>k__BackingField","Offset":40,"LayoutOffset":-1,"Specifiers":["private"],"Type":{"Namespace":"","Name":"BeatmapDifficulty","IsGenericParameter":false,"IsArray":false,"IsPointer":false,"Generics":[],"TypeId":0},"Constant":null}],"Layout":"Auto","Methods":[{"Attributes":[{"Name":"TokenAttribute","RVA":-1,"Offset":-1,"VA":-1},{"Name":"CompilerGeneratedAttribute","RVA":15007784,"Offset":15007784,"VA":-1}],"Generic":false,"GenericParameters":[],"HidesBase":false,"Il2CppName":"get_beatmapLevel","ImplementedFrom":null,"IsSpecialName":false,"IsVirtual":true,"Name":"get_beatmapLevel","Offset":18438932,"Parameters":[],"ReturnType":{"Namespace":"","Name":"IPreviewBeatmapLevel","IsGenericParameter":false,"IsArray":false,"IsPointer":false,"Generics":[],"TypeId":1641},"RVA":18438932,"Slot":4,"Specifiers":["public"],"VA":18438932},{"Attributes":[{"Name":"TokenAttribute","RVA":-1,"Offset":-1,"VA":-1},{"Name":"CompilerGeneratedAttribute","RVA":15007800,"Offset":15007800,"VA":-1}],"Generic":false,"GenericParameters":[],"HidesBase":false,"Il2CppName":"set_beatmapLevel","ImplementedFrom":null,"IsSpecialName":false,"IsVirtual":true,"Name":"set_beatmapLevel","Offset":18438940,"Parameters":[{"Type":{"Namespace":"","Name":"IPreviewBeatmapLevel","IsGenericParameter":false,"IsArray":false,"IsPointer":false,"Generics":[],"TypeId":1641},"Name":"value","Modifier":"None"}],"ReturnType":{"Namespace":"System","Name":"Void","IsGenericParameter":false,"IsArray":false,"IsPointer":false,"Generics":[],"TypeId":3047},"RVA":18438940,"Slot":5,"Specifiers":["public"],"VA":18438940},{"Attributes":[{"Name":"TokenAttribute","RVA":-1,"Offset":-1,"VA":-1},{"Name":"CompilerGeneratedAttribute","RVA":15007816,"Offset":15007816,"VA":-1}],"Generic":false,"GenericParameters":[],"HidesBase":false,"Il2CppName":"get_beatmapCharacteristic","ImplementedFrom":null,"IsSpecialName":false,"IsVirtual":true,"Name":"get_beatmapCharacteristic","Offset":18438948,"Parameters":[],"ReturnType":{"Namespace":"","Name":"BeatmapCharacteristicSO","IsGenericParameter":false,"IsArray":false,"IsPointer":false,"Generics":[],"TypeId":1596},"RVA":18438948,"Slot":6,"Specifiers":["public"],"VA":18438948},{"Attributes":[{"Name":"TokenAttribute","RVA":-1,"Offset":-1,"VA":-1},{"Name":"CompilerGeneratedAttribute","RVA":15007832,"Offset":15007832,"VA":-1}],"Generic":false,"GenericParameters":[],"HidesBase":false,"Il2CppName":"set_beatmapCharacteristic","ImplementedFrom":null,"IsSpecialName":false,"IsVirtual":true,"Name":"set_beatmapCharacteristic","Offset":18438956,"Parameters":[{"Type":{"Namespace":"","Name":"BeatmapCharacteristicSO","IsGenericParameter":false,"IsArray":false,"IsPointer":false,"Generics":[],"TypeId":1596},"Name":"value","Modifier":"None"}],"ReturnType":{"Namespace":"System","Name":"Void","IsGenericParameter":false,"IsArray":false,"IsPointer":false,"Generics":[],"TypeId":3047},"RVA":18438956,"Slot":7,"Specifiers":["public"],"VA":18438956},{"Attributes":[{"Name":"TokenAttribute","RVA":-1,"Offset":-1,"VA":-1},{"Name":"CompilerGeneratedAttribute","RVA":15007848,"Offset":15007848,"VA":-1}],"Generic":false,"GenericParameters":[],"HidesBase":false,"Il2CppName":"get_beatmapDifficulty","ImplementedFrom":null,"IsSpecialName":false,"IsVirtual":true,"Name":"get_beatmapDifficulty","Offset":18438964,"Parameters":[],"ReturnType":{"Namespace":"","Name":"BeatmapDifficulty","IsGenericParameter":false,"IsArray":false,"IsPointer":false,"Generics":[],"TypeId":0},"RVA":18438964,"Slot":8,"Specifiers":["public"],"VA":18438964},{"Attributes":[{"Name":"TokenAttribute","RVA":-1,"Offset":-1,"VA":-1},{"Name":"CompilerGeneratedAttribute","RVA":15007864,"Offset":15007864,"VA":-1}],"Generic":false,"GenericParameters":[],"HidesBase":false,"Il2CppName":"set_beatmapDifficulty","ImplementedFrom":null,"IsSpecialName":false,"IsVirtual":true,"Name":"set_beatmapDifficulty","Offset":18438972,"Parameters":[{"Type":{"Namespace":"","Name":"BeatmapDifficulty","IsGenericParameter":false,"IsArray":false,"IsPointer":false,"Generics":[],"TypeId":0},"Name":"value","Modifier":"None"}],"ReturnType":{"Namespace":"System","Name":"Void","IsGenericParameter":false,"IsArray":false,"IsPointer":false,"Generics":[],"TypeId":3047},"RVA":18438972,"Slot":9,"Specifiers":["public"],"VA":18438972},{"Attributes":[{"Name":"TokenAttribute","RVA":-1,"Offset":-1,"VA":-1}],"Generic":false,"GenericParameters":[],"HidesBase":false,"Il2CppName":"get_gameplayModifiers","ImplementedFrom":null,"IsSpecialName":false,"IsVirtual":true,"Name":"get_gameplayModifiers","Offset":18438980,"Parameters":[],"ReturnType":{"Namespace":"","Name":"GameplayModifiers","IsGenericParameter":false,"IsArray":false,"IsPointer":false,"Generics":[],"TypeId":1008},"RVA":18438980,"Slot":10,"Specifiers":["public"],"VA":18438980},{"Attributes":[{"Name":"TokenAttribute","RVA":-1,"Offset":-1,"VA":-1}],"Generic":false,"GenericParameters":[],"HidesBase":false,"Il2CppName":"set_gameplayModifiers","ImplementedFrom":null,"IsSpecialName":false,"IsVirtual":true,"Name":"set_gameplayModifiers","Offset":18439088,"Parameters":[{"Type":{"Namespace":"","Name":"GameplayModifiers","IsGenericParameter":false,"IsArray":false,"IsPointer":false,"Generics":[],"TypeId":1008},"Name":"value","Modifier":"None"}],"ReturnType":{"Namespace":"System","Name":"Void","IsGenericParameter":false,"IsArray":false,"IsPointer":false,"Generics":[],"TypeId":3047},"RVA":18439088,"Slot":11,"Specifiers":["public"],"VA":18439088},{"Attributes":[{"Name":"TokenAttribute","RVA":-1,"Offset":-1,"VA":-1}],"Generic":false,"GenericParameters":[],"HidesBase":true,"Il2CppName":".ctor","ImplementedFrom":{"Namespace":"System","Name":"Object","IsGenericParameter":false,"IsArray":false,"IsPointer":false,"Generics":[],"TypeId":3015},"IsSpecialName":false,"IsVirtual":false,"Name":".ctor","Offset":18439096,"Parameters":[],"ReturnType":{"Namespace":"System","Name":"Void","IsGenericParameter":false,"IsArray":false,"IsPointer":false,"Generics":[],"TypeId":3047},"RVA":18439096,"Slot":-1,"Specifiers":["public"],"VA":18439096}],"NestedTypes":[],"Parent":{"Namespace":"System","Name":"Object","IsGenericParameter":false,"IsArray":false,"IsPointer":false,"Generics":[],"TypeId":3015},"Properties":[{"Attributes":[{"Name":"TokenAttribute","RVA":-1,"Offset":-1,"VA":-1}],"Specifiers":["public"],"GetMethod":true,"SetMethod":true,"Name":"beatmapLevel","Type":{"Namespace":"","Name":"IPreviewBeatmapLevel","IsGenericParameter":false,"IsArray":false,"IsPointer":false,"Generics":[],"TypeId":1641}},{"Attributes":[{"Name":"TokenAttribute","RVA":-1,"Offset":-1,"VA":-1}],"Specifiers":["public"],"GetMethod":true,"SetMethod":true,"Name":"beatmapCharacteristic","Type":{"Namespace":"","Name":"BeatmapCharacteristicSO","IsGenericParameter":false,"IsArray":false,"IsPointer":false,"Generics":[],"TypeId":1596}},{"Attributes":[{"Name":"TokenAttribute","RVA":-1,"Offset":-1,"VA":-1}],"Specifiers":["public"],"GetMethod":true,"SetMethod":true,"Name":"beatmapDifficulty","Type":{"Namespace":"","Name":"BeatmapDifficulty","IsGenericParameter":false,"IsArray":false,"IsPointer":false,"Generics":[],"TypeId":0}},{"Attributes":[{"Name":"TokenAttribute","RVA":-1,"Offset":-1,"VA":-1}],"Specifiers":["public"],"GetMethod":true,"SetMethod":true,"Name":"gameplayModifiers","Type":{"Namespace":"","Name":"GameplayModifiers","IsGenericParameter":false,"IsArray":false,"IsPointer":false,"Generics":[],"TypeId":1008}}],"Specifiers":[],"StaticFields":[],"Type":"Class","TypeDefIndex":-1,"Size":44}