{"This":{"Namespace":"System.Runtime.Remoting","Name":"IEnvoyInfo","QualifiedCppName":"System::Runtime::Remoting::IEnvoyInfo","IsGenericTemplate":false,"IsNested":false,"ElementType":null,"GenericParameterConstraints":[],"Generics":[]},"Attributes":[{"Name":"TokenAttribute","RVA":-1,"Offset":-1,"VA":-1},{"Name":"ComVisibleAttribute","RVA":14299780,"Offset":14299780,"VA":-1}],"ImplementingInterfaces":[],"InstanceFields":[],"Layout":"Auto","Methods":[{"Attributes":[{"Name":"TokenAttribute","RVA":-1,"Offset":-1,"VA":-1}],"Generic":false,"GenericParameters":[],"HidesBase":false,"Il2CppName":"get_EnvoySinks","ImplementedFrom":null,"IsSpecialName":false,"IsVirtual":true,"Name":"get_EnvoySinks","Offset":-1,"Parameters":[],"ReturnType":{"Namespace":"System.Runtime.Remoting.Messaging","Name":"IMessageSink","IsGenericParameter":false,"IsArray":false,"IsPointer":false,"Generics":[],"TypeId":3732},"RVA":-1,"Slot":-1,"Specifiers":["public"],"VA":-1}],"NestedTypes":[],"Parent":null,"Properties":[{"Attributes":[{"Name":"TokenAttribute","RVA":-1,"Offset":-1,"VA":-1}],"Specifiers":["public"],"GetMethod":true,"SetMethod":false,"Name":"EnvoySinks","Type":{"Namespace":"System.Runtime.Remoting.Messaging","Name":"IMessageSink","IsGenericParameter":false,"IsArray":false,"IsPointer":false,"Generics":[],"TypeId":3732}}],"Specifiers":[],"StaticFields":[],"Type":"Interface","TypeDefIndex":-1,"Size":0}